hypso2_calibration/__init__.py
hypso2_calibration/main.py
hypso2_calibration/data/EQM_spectral_coeffs_fluorescent_before_shock_vib.npz
hypso2_calibration/data/FM_pre_spectral_coeffs.npz
hypso2_calibration/data/h2_radiometric_calibration_matrix_full.npz
hypso2_calibration/data/h2_radiometric_calibration_matrix_wide.npz
hypso2_calibration/data/h2_spectral_calibration_coefficients.npz
hypso2_calibration/data/h2_spectral_calibration_matrix.npz
hypso2_calibration/data/h2_spectral_calibration_matrix_smoothed.npz
hypso2_calibration/data/h2_spectral_calibration_wavelengths_center_row.npz
hypso2_calibration/data/spectral_bands_HYPSO-2.npz
hypso2_calibration-25.10.0b1.dist-info/METADATA
hypso2_calibration-25.10.0b1.dist-info/WHEEL
hypso2_calibration-25.10.0b1.dist-info/top_level.txt
hypso2_calibration-25.10.0b1.dist-info/RECORD
