Metadata-Version: 2.4
Name: hypso2_calibration
Version: 25.10.0b1
Summary: HYPSO-2 Calibration Files for HYPSO Toolbox
Author-email: Cameron Penne <cameron.l.penne@ntnu.no>
Maintainer-email: Cameron Penne <cameron.l.penne@ntnu.no>
License: MIT
Project-URL: Homepage, https://github.com/NTNU-SmallSat-Lab/hypso-package
Project-URL: Bug Tracker, https://github.com/NTNU-SmallSat-Lab/hypso-package/issues
Classifier: Programming Language :: Python :: 3.10
Classifier: Programming Language :: Python :: 3.11
Classifier: Programming Language :: Python :: 3.12
Classifier: Programming Language :: Python :: 3.13
Classifier: License :: OSI Approved :: MIT License
Classifier: Operating System :: OS Independent
Requires-Python: >=3.10
Requires-Dist: numpy>=1.24
